flask_was
